odoo/addons/ssi_stock_location_m2o_configurator_mixin/README.rst
odoo/addons/ssi_stock_location_m2o_configurator_mixin/__init__.py
odoo/addons/ssi_stock_location_m2o_configurator_mixin/__manifest__.py
odoo/addons/ssi_stock_location_m2o_configurator_mixin/models/__init__.py
odoo/addons/ssi_stock_location_m2o_configurator_mixin/models/mixin_inbound_stock_location_m2o_configurator.py
odoo/addons/ssi_stock_location_m2o_configurator_mixin/models/mixin_outbound_stock_location_m2o_configurator.py
odoo/addons/ssi_stock_location_m2o_configurator_mixin/models/mixin_stock_location_m2o_configurator.py
odoo/addons/ssi_stock_location_m2o_configurator_mixin/static/description/icon.png
odoo/addons/ssi_stock_location_m2o_configurator_mixin/templates/inbound_stock_location_m2_configurator_templates.xml
odoo/addons/ssi_stock_location_m2o_configurator_mixin/templates/outbound_stock_location_m2_configurator_templates.xml
odoo/addons/ssi_stock_location_m2o_configurator_mixin/templates/stock_location_m2_configurator_templates.xml
odoo14_addon_ssi_stock_location_m2o_configurator_mixin-14.0.1.0.0.dist-info/METADATA
odoo14_addon_ssi_stock_location_m2o_configurator_mixin-14.0.1.0.0.dist-info/WHEEL
odoo14_addon_ssi_stock_location_m2o_configurator_mixin-14.0.1.0.0.dist-info/top_level.txt
odoo14_addon_ssi_stock_location_m2o_configurator_mixin-14.0.1.0.0.dist-info/RECORD
